<?xml version="1.0" encoding="utf-8"?>
<clothing-items>
 <clothing>
  <id>
   196696289
  </id>
  <name>
   Puma Hat M-9267
  </name>
  <category>
   Hat
  </category>
  <size>
   M
  </size>
  <color>
   Голубой
  </color>
  <material>
   Полиэстер
  </material>
  <price>
   674683
  </price>
  <rating>
   4.09
  </rating>
  <reviews>
   516820
  </reviews>
  <new>
   -
  </new>
  <sporty>
   yes
  </sporty>
 </clothing>
 <clothing>
  <id>
   653124616
  </id>
  <name>
   DC Jacket M-2301
  </name>
  <category>
   Jacket
  </category>
  <size>
   XXL
  </size>
  <color>
   Оранжевый
  </color>
  <material>
   Шерсть
  </material>
  <price>
   188707
  </price>
  <rating>
   4.39
  </rating>
  <reviews>
   995175
  </reviews>
  <new>
   +
  </new>
  <sporty>
   no
  </sporty>
 </clothing>
 <clothing>
  <id>
   183288943
  </id>
  <name>
   Brooks Jacket Z-6960
  </name>
  <category>
   Jacket
  </category>
  <size>
   XXL
  </size>
  <color>
   Оранжевый
  </color>
  <material>
   Хлопок
  </material>
  <price>
   748749
  </price>
  <rating>
   3.93
  </rating>
  <reviews>
   214037
  </reviews>
  <new>
   -
  </new>
  <sporty>
   no
  </sporty>
 </clothing>
 <clothing>
  <id>
   963053626
  </id>
  <name>
   Nike Pants T-8901
  </name>
  <category>
   Pants
  </category>
  <size>
   XXL
  </size>
  <color>
   Голубой
  </color>
  <material>
   Вискоза
  </material>
  <price>
   839667
  </price>
  <rating>
   4.91
  </rating>
  <reviews>
   439383
  </reviews>
  <new>
   -
  </new>
  <exclusive>
   yes
  </exclusive>
  <sporty>
   yes
  </sporty>
 </clothing>
 <clothing>
  <id>
   748779653
  </id>
  <name>
   Reebok Hat R-5860
  </name>
  <category>
   Hat
  </category>
  <size>
   M
  </size>
  <color>
   Голубой
  </color>
  <material>
   Шелк
  </material>
  <price>
   221307
  </price>
  <rating>
   4.4
  </rating>
  <reviews>
   680409
  </reviews>
  <new>
   -
  </new>
  <sporty>
   no
  </sporty>
 </clothing>
 <clothing>
  <id>
   939292443
  </id>
  <name>
   New Balance Shoes S-8988
  </name>
  <category>
   Shoes
  </category>
  <size>
   XXL
  </size>
  <color>
   Оранжевый
  </color>
  <material>
   Шерсть
  </material>
  <price>
   847740
  </price>
  <rating>
   4.18
  </rating>
  <reviews>
   431926
  </reviews>
  <sporty>
   no
  </sporty>
 </clothing>
 <clothing>
  <id>
   128049601
  </id>
  <name>
   Brooks Shoes X-8983
  </name>
  <category>
   Shoes
  </category>
  <size>
   S
  </size>
  <color>
   Голубой
  </color>
  <material>
   Полиэстер
  </material>
  <price>
   883780
  </price>
  <rating>
   4.28
  </rating>
  <reviews>
   569887
  </reviews>
  <new>
   -
  </new>
  <sporty>
   yes
  </sporty>
 </clothing>
 <clothing>
  <id>
   544467279
  </id>
  <name>
   Brooks Jeans H-7417
  </name>
  <category>
   Jeans
  </category>
  <size>
   M
  </size>
  <color>
   Желтый
  </color>
  <material>
   Лен
  </material>
  <price>
   898981
  </price>
  <rating>
   3.82
  </rating>
  <reviews>
   742754
  </reviews>
  <exclusive>
   no
  </exclusive>
  <sporty>
   yes
  </sporty>
 </clothing>
 <clothing>
  <id>
   477308017
  </id>
  <name>
   Addidas Blouse Z-4579
  </name>
  <category>
   Blouse
  </category>
  <size>
   XXL
  </size>
  <color>
   Оранжевый
  </color>
  <material>
   Вискоза
  </material>
  <price>
   286884
  </price>
  <rating>
   2.34
  </rating>
  <reviews>
   691336
  </reviews>
  <exclusive>
   no
  </exclusive>
  <sporty>
   no
  </sporty>
 </clothing>
 <clothing>
  <id>
   564816338
  </id>
  <name>
   New Balance Shoes X-2706
  </name>
  <category>
   Shoes
  </category>
  <size>
   M
  </size>
  <color>
   Фиолетовый
  </color>
  <material>
   Кожа
  </material>
  <price>
   404478
  </price>
  <rating>
   2.75
  </rating>
  <reviews>
   466645
  </reviews>
  <new>
   +
  </new>
 </clothing>
 <clothing>
  <id>
   642807016
  </id>
  <name>
   New Balance Blouse B-6879
  </name>
  <category>
   Blouse
  </category>
  <size>
   XXL
  </size>
  <color>
   Зеленый
  </color>
  <material>
   Шелк
  </material>
  <price>
   844615
  </price>
  <rating>
   2.84
  </rating>
  <reviews>
   617473
  </reviews>
 </clothing>
 <clothing>
  <id>
   948717384
  </id>
  <name>
   Ellesse Belts O-4461
  </name>
  <category>
   Belts
  </category>
  <size>
   XXL
  </size>
  <color>
   Голубой
  </color>
  <material>
   Шерсть
  </material>
  <price>
   254901
  </price>
  <rating>
   4.99
  </rating>
  <reviews>
   522529
  </reviews>
  <new>
   -
  </new>
  <exclusive>
   no
  </exclusive>
  <sporty>
   yes
  </sporty>
 </clothing>
 <clothing>
  <id>
   595340240
  </id>
  <name>
   Vans Handbags Y-7340
  </name>
  <category>
   Handbags
  </category>
  <size>
   M
  </size>
  <color>
   Зеленый
  </color>
  <material>
   Вискоза
  </material>
  <price>
   933529
  </price>
  <rating>
   3.38
  </rating>
  <reviews>
   977687
  </reviews>
  <new>
   +
  </new>
  <exclusive>
   no
  </exclusive>
 </clothing>
 <clothing>
  <id>
   551152478
  </id>
  <name>
   Brooks Pants M-2775
  </name>
  <category>
   Pants
  </category>
  <size>
   M
  </size>
  <color>
   Красный
  </color>
  <material>
   Полиэстер
  </material>
  <price>
   982436
  </price>
  <rating>
   3.37
  </rating>
  <reviews>
   65321
  </reviews>
  <new>
   -
  </new>
  <sporty>
   no
  </sporty>
 </clothing>
 <clothing>
  <id>
   749497421
  </id>
  <name>
   Fila Umbrellas W-6791
  </name>
  <category>
   Umbrellas
  </category>
  <size>
   XXL
  </size>
  <color>
   Голубой
  </color>
  <material>
   Кожа
  </material>
  <price>
   261143
  </price>
  <rating>
   1.35
  </rating>
  <reviews>
   481340
  </reviews>
  <exclusive>
   no
  </exclusive>
  <sporty>
   no
  </sporty>
 </clothing>
 <clothing>
  <id>
   403922241
  </id>
  <name>
   New Balance Umbrellas I-8032
  </name>
  <category>
   Umbrellas
  </category>
  <size>
   M
  </size>
  <color>
   Красный
  </color>
  <material>
   Шерсть
  </material>
  <price>
   171739
  </price>
  <rating>
   3.44
  </rating>
  <reviews>
   170375
  </reviews>
  <exclusive>
   no
  </exclusive>
 </clothing>
 <clothing>
  <id>
   794276585
  </id>
  <name>
   Adidas Gloves R-5615
  </name>
  <category>
   Gloves
  </category>
  <size>
   M
  </size>
  <color>
   Зеленый
  </color>
  <material>
   Нейлон
  </material>
  <price>
   388510
  </price>
  <rating>
   4.58
  </rating>
  <reviews>
   199165
  </reviews>
  <exclusive>
   no
  </exclusive>
  <sporty>
   yes
  </sporty>
 </clothing>
 <clothing>
  <id>
   126532029
  </id>
  <name>
   Fila Belts Z-6722
  </name>
  <category>
   Belts
  </category>
  <size>
   S
  </size>
  <color>
   Синий
  </color>
  <material>
   Кожа
  </material>
  <price>
   748416
  </price>
  <rating>
   4.12
  </rating>
  <reviews>
   557153
  </reviews>
  <new>
   -
  </new>
  <exclusive>
   no
  </exclusive>
 </clothing>
 <clothing>
  <id>
   875444357
  </id>
  <name>
   Fila Gloves B-5849
  </name>
  <category>
   Gloves
  </category>
  <size>
   M
  </size>
  <color>
   Оранжевый
  </color>
  <material>
   Лен
  </material>
  <price>
   946203
  </price>
  <rating>
   4.25
  </rating>
  <reviews>
   908286
  </reviews>
 </clothing>
 <clothing>
  <id>
   722987647
  </id>
  <name>
   Reebok Belts L-2090
  </name>
  <category>
   Belts
  </category>
  <size>
   XL
  </size>
  <color>
   Голубой
  </color>
  <material>
   Полиэстер
  </material>
  <price>
   456106
  </price>
  <rating>
   2.75
  </rating>
  <reviews>
   798160
  </reviews>
 </clothing>
 <clothing>
  <id>
   812569135
  </id>
  <name>
   Vans Shoes T-3230
  </name>
  <category>
   Shoes
  </category>
  <size>
   XL
  </size>
  <color>
   Фиолетовый
  </color>
  <material>
   Нейлон
  </material>
  <price>
   330635
  </price>
  <rating>
   2.52
  </rating>
  <reviews>
   436102
  </reviews>
  <new>
   -
  </new>
  <exclusive>
   no
  </exclusive>
  <sporty>
   no
  </sporty>
 </clothing>
 <clothing>
  <id>
   304986591
  </id>
  <name>
   PleinSport Belts E-9527
  </name>
  <category>
   Belts
  </category>
  <size>
   XXL
  </size>
  <color>
   Фиолетовый
  </color>
  <material>
   Шерсть
  </material>
  <price>
   767045
  </price>
  <rating>
   1.88
  </rating>
  <reviews>
   710941
  </reviews>
  <new>
   -
  </new>
  <exclusive>
   no
  </exclusive>
  <sporty>
   no
  </sporty>
 </clothing>
 <clothing>
  <id>
   990754745
  </id>
  <name>
   Lacoste Handbags E-1819
  </name>
  <category>
   Handbags
  </category>
  <size>
   S
  </size>
  <color>
   Фиолетовый
  </color>
  <material>
   Хлопок
  </material>
  <price>
   210260
  </price>
  <rating>
   2.03
  </rating>
  <reviews>
   165167
  </reviews>
  <exclusive>
   yes
  </exclusive>
  <sporty>
   no
  </sporty>
 </clothing>
 <clothing>
  <id>
   365414619
  </id>
  <name>
   Ellesse Umbrellas R-7336
  </name>
  <category>
   Umbrellas
  </category>
  <size>
   M
  </size>
  <color>
   Зеленый
  </color>
  <material>
   Шерсть
  </material>
  <price>
   886895
  </price>
  <rating>
   4.77
  </rating>
  <reviews>
   56572
  </reviews>
  <new>
   +
  </new>
  <exclusive>
   yes
  </exclusive>
  <sporty>
   no
  </sporty>
 </clothing>
 <clothing>
  <id>
   624018527
  </id>
  <name>
   Vans Umbrellas N-2211
  </name>
  <category>
   Umbrellas
  </category>
  <size>
   S
  </size>
  <color>
   Синий
  </color>
  <material>
   Кожа
  </material>
  <price>
   594908
  </price>
  <rating>
   1.17
  </rating>
  <reviews>
   832442
  </reviews>
  <new>
   -
  </new>
 </clothing>
 <clothing>
  <id>
   187342902
  </id>
  <name>
   Ellesse Dress U-4537
  </name>
  <category>
   Dress
  </category>
  <size>
   XXL
  </size>
  <color>
   Оранжевый
  </color>
  <material>
   Лен
  </material>
  <price>
   862676
  </price>
  <rating>
   2.31
  </rating>
  <reviews>
   957035
  </reviews>
  <sporty>
   no
  </sporty>
 </clothing>
 <clothing>
  <id>
   950623409
  </id>
  <name>
   Brooks Gloves P-8206
  </name>
  <category>
   Gloves
  </category>
  <size>
   XL
  </size>
  <color>
   Зеленый
  </color>
  <material>
   Шерсть
  </material>
  <price>
   863995
  </price>
  <rating>
   3.31
  </rating>
  <reviews>
   528396
  </reviews>
  <exclusive>
   no
  </exclusive>
  <sporty>
   no
  </sporty>
 </clothing>
 <clothing>
  <id>
   902880797
  </id>
  <name>
   Fila Shirt R-5649
  </name>
  <category>
   Shirt
  </category>
  <size>
   S
  </size>
  <color>
   Голубой
  </color>
  <material>
   Кожа
  </material>
  <price>
   445423
  </price>
  <rating>
   4.84
  </rating>
  <reviews>
   761984
  </reviews>
  <new>
   +
  </new>
  <exclusive>
   yes
  </exclusive>
  <sporty>
   yes
  </sporty>
 </clothing>
 <clothing>
  <id>
   454488772
  </id>
  <name>
   Reebok Dress D-5960
  </name>
  <category>
   Dress
  </category>
  <size>
   L
  </size>
  <color>
   Оранжевый
  </color>
  <material>
   Нейлон
  </material>
  <price>
   460714
  </price>
  <rating>
   4.54
  </rating>
  <reviews>
   444304
  </reviews>
  <sporty>
   yes
  </sporty>
 </clothing>
 <clothing>
  <id>
   305721416
  </id>
  <name>
   PleinSport Gloves R-9809
  </name>
  <category>
   Gloves
  </category>
  <size>
   S
  </size>
  <color>
   Красный
  </color>
  <material>
   Хлопок
  </material>
  <price>
   970550
  </price>
  <rating>
   3.48
  </rating>
  <reviews>
   236243
  </reviews>
  <sporty>
   no
  </sporty>
 </clothing>
 <clothing>
  <id>
   371827414
  </id>
  <name>
   Brooks Pants O-7853
  </name>
  <category>
   Pants
  </category>
  <size>
   XL
  </size>
  <color>
   Желтый
  </color>
  <material>
   Вискоза
  </material>
  <price>
   730932
  </price>
  <rating>
   2.81
  </rating>
  <reviews>
   111418
  </reviews>
  <new>
   -
  </new>
  <exclusive>
   yes
  </exclusive>
  <sporty>
   no
  </sporty>
 </clothing>
 <clothing>
  <id>
   736231611
  </id>
  <name>
   Reebok Dress F-6166
  </name>
  <category>
   Dress
  </category>
  <size>
   XXL
  </size>
  <color>
   Синий
  </color>
  <material>
   Шелк
  </material>
  <price>
   907425
  </price>
  <rating>
   2.27
  </rating>
  <reviews>
   837531
  </reviews>
 </clothing>
 <clothing>
  <id>
   378624754
  </id>
  <name>
   Puma Dress K-6089
  </name>
  <category>
   Dress
  </category>
  <size>
   XL
  </size>
  <color>
   Фиолетовый
  </color>
  <material>
   Полиэстер
  </material>
  <price>
   788498
  </price>
  <rating>
   3.26
  </rating>
  <reviews>
   707615
  </reviews>
  <new>
   -
  </new>
  <sporty>
   no
  </sporty>
 </clothing>
 <clothing>
  <id>
   236646188
  </id>
  <name>
   Converse Gloves R-9053
  </name>
  <category>
   Gloves
  </category>
  <size>
   XXL
  </size>
  <color>
   Фиолетовый
  </color>
  <material>
   Нейлон
  </material>
  <price>
   385428
  </price>
  <rating>
   3.15
  </rating>
  <reviews>
   74718
  </reviews>
  <exclusive>
   no
  </exclusive>
  <sporty>
   no
  </sporty>
 </clothing>
</clothing-items>
