<?xml version="1.0" encoding="utf-8"?>
<clothing-items>
 <clothing>
  <id>
   605740304
  </id>
  <name>
   Adidas Shoes K-8900
  </name>
  <category>
   Shoes
  </category>
  <size>
   XL
  </size>
  <color>
   Желтый
  </color>
  <material>
   Лен
  </material>
  <price>
   760521
  </price>
  <rating>
   4.17
  </rating>
  <reviews>
   757554
  </reviews>
  <new>
   -
  </new>
  <exclusive>
   no
  </exclusive>
  <sporty>
   no
  </sporty>
 </clothing>
 <clothing>
  <id>
   473874660
  </id>
  <name>
   PleinSport Umbrellas V-5316
  </name>
  <category>
   Umbrellas
  </category>
  <size>
   XXL
  </size>
  <color>
   Желтый
  </color>
  <material>
   Лен
  </material>
  <price>
   374009
  </price>
  <rating>
   4.9
  </rating>
  <reviews>
   724258
  </reviews>
  <exclusive>
   no
  </exclusive>
  <sporty>
   no
  </sporty>
 </clothing>
 <clothing>
  <id>
   414403485
  </id>
  <name>
   Asics Dress Z-7729
  </name>
  <category>
   Dress
  </category>
  <size>
   XL
  </size>
  <color>
   Оранжевый
  </color>
  <material>
   Полиэстер
  </material>
  <price>
   263829
  </price>
  <rating>
   4.89
  </rating>
  <reviews>
   162482
  </reviews>
 </clothing>
 <clothing>
  <id>
   934230341
  </id>
  <name>
   PleinSport Umbrellas Z-4047
  </name>
  <category>
   Umbrellas
  </category>
  <size>
   L
  </size>
  <color>
   Голубой
  </color>
  <material>
   Хлопок
  </material>
  <price>
   792345
  </price>
  <rating>
   2.8
  </rating>
  <reviews>
   135245
  </reviews>
  <exclusive>
   no
  </exclusive>
  <sporty>
   yes
  </sporty>
 </clothing>
 <clothing>
  <id>
   236210634
  </id>
  <name>
   Puma T-shirt A-8758
  </name>
  <category>
   T-shirt
  </category>
  <size>
   XXL
  </size>
  <color>
   Фиолетовый
  </color>
  <material>
   Вискоза
  </material>
  <price>
   988084
  </price>
  <rating>
   4.64
  </rating>
  <reviews>
   838683
  </reviews>
  <new>
   -
  </new>
 </clothing>
 <clothing>
  <id>
   919881096
  </id>
  <name>
   Asics Jeans Y-4139
  </name>
  <category>
   Jeans
  </category>
  <size>
   L
  </size>
  <color>
   Синий
  </color>
  <material>
   Нейлон
  </material>
  <price>
   398627
  </price>
  <rating>
   1.33
  </rating>
  <reviews>
   681303
  </reviews>
  <new>
   -
  </new>
  <exclusive>
   yes
  </exclusive>
 </clothing>
 <clothing>
  <id>
   181885513
  </id>
  <name>
   Converse T-shirt A-9401
  </name>
  <category>
   T-shirt
  </category>
  <size>
   XXL
  </size>
  <color>
   Синий
  </color>
  <material>
   Нейлон
  </material>
  <price>
   325200
  </price>
  <rating>
   1.42
  </rating>
  <reviews>
   167267
  </reviews>
  <sporty>
   yes
  </sporty>
 </clothing>
 <clothing>
  <id>
   118048529
  </id>
  <name>
   PleinSport Socks N-3016
  </name>
  <category>
   Socks
  </category>
  <size>
   XXL
  </size>
  <color>
   Красный
  </color>
  <material>
   Лен
  </material>
  <price>
   514865
  </price>
  <rating>
   3.88
  </rating>
  <reviews>
   402165
  </reviews>
  <exclusive>
   no
  </exclusive>
 </clothing>
 <clothing>
  <id>
   398955132
  </id>
  <name>
   Asics Hat I-9138
  </name>
  <category>
   Hat
  </category>
  <size>
   S
  </size>
  <color>
   Зеленый
  </color>
  <material>
   Кожа
  </material>
  <price>
   950495
  </price>
  <rating>
   4.32
  </rating>
  <reviews>
   226551
  </reviews>
  <new>
   -
  </new>
 </clothing>
 <clothing>
  <id>
   345266585
  </id>
  <name>
   DC Jeans U-7886
  </name>
  <category>
   Jeans
  </category>
  <size>
   XXL
  </size>
  <color>
   Голубой
  </color>
  <material>
   Хлопок
  </material>
  <price>
   106471
  </price>
  <rating>
   2.74
  </rating>
  <reviews>
   492898
  </reviews>
  <sporty>
   yes
  </sporty>
 </clothing>
 <clothing>
  <id>
   407265978
  </id>
  <name>
   Addidas Sweater T-6947
  </name>
  <category>
   Sweater
  </category>
  <size>
   M
  </size>
  <color>
   Желтый
  </color>
  <material>
   Хлопок
  </material>
  <price>
   987867
  </price>
  <rating>
   3.06
  </rating>
  <reviews>
   194857
  </reviews>
  <new>
   +
  </new>
  <exclusive>
   no
  </exclusive>
 </clothing>
 <clothing>
  <id>
   941453233
  </id>
  <name>
   Fila Blouse B-1161
  </name>
  <category>
   Blouse
  </category>
  <size>
   XXL
  </size>
  <color>
   Зеленый
  </color>
  <material>
   Шерсть
  </material>
  <price>
   108621
  </price>
  <rating>
   2.31
  </rating>
  <reviews>
   203678
  </reviews>
  <sporty>
   no
  </sporty>
 </clothing>
 <clothing>
  <id>
   782706109
  </id>
  <name>
   Fila Belts K-1730
  </name>
  <category>
   Belts
  </category>
  <size>
   XXL
  </size>
  <color>
   Красный
  </color>
  <material>
   Нейлон
  </material>
  <price>
   376506
  </price>
  <rating>
   3.31
  </rating>
  <reviews>
   850901
  </reviews>
  <new>
   +
  </new>
  <exclusive>
   no
  </exclusive>
 </clothing>
 <clothing>
  <id>
   846794179
  </id>
  <name>
   Under Armour Belts V-8863
  </name>
  <category>
   Belts
  </category>
  <size>
   S
  </size>
  <color>
   Синий
  </color>
  <material>
   Шелк
  </material>
  <price>
   662478
  </price>
  <rating>
   5.0
  </rating>
  <reviews>
   123049
  </reviews>
  <new>
   +
  </new>
  <exclusive>
   no
  </exclusive>
 </clothing>
 <clothing>
  <id>
   504452454
  </id>
  <name>
   Reebok Shoes X-6749
  </name>
  <category>
   Shoes
  </category>
  <size>
   XXL
  </size>
  <color>
   Зеленый
  </color>
  <material>
   Шелк
  </material>
  <price>
   560703
  </price>
  <rating>
   2.14
  </rating>
  <reviews>
   213955
  </reviews>
  <exclusive>
   yes
  </exclusive>
  <sporty>
   no
  </sporty>
 </clothing>
 <clothing>
  <id>
   751263476
  </id>
  <name>
   Reebok Dress A-3005
  </name>
  <category>
   Dress
  </category>
  <size>
   S
  </size>
  <color>
   Зеленый
  </color>
  <material>
   Шерсть
  </material>
  <price>
   361771
  </price>
  <rating>
   2.77
  </rating>
  <reviews>
   909604
  </reviews>
  <sporty>
   yes
  </sporty>
 </clothing>
 <clothing>
  <id>
   926776766
  </id>
  <name>
   Fila T-shirt H-3367
  </name>
  <category>
   T-shirt
  </category>
  <size>
   M
  </size>
  <color>
   Оранжевый
  </color>
  <material>
   Шелк
  </material>
  <price>
   964196
  </price>
  <rating>
   3.43
  </rating>
  <reviews>
   257087
  </reviews>
  <new>
   +
  </new>
  <exclusive>
   no
  </exclusive>
 </clothing>
 <clothing>
  <id>
   451585489
  </id>
  <name>
   Ellesse Blouse G-3087
  </name>
  <category>
   Blouse
  </category>
  <size>
   XXL
  </size>
  <color>
   Голубой
  </color>
  <material>
   Шерсть
  </material>
  <price>
   782997
  </price>
  <rating>
   3.87
  </rating>
  <reviews>
   82590
  </reviews>
  <sporty>
   no
  </sporty>
 </clothing>
 <clothing>
  <id>
   112460350
  </id>
  <name>
   Ellesse Gloves F-5768
  </name>
  <category>
   Gloves
  </category>
  <size>
   L
  </size>
  <color>
   Желтый
  </color>
  <material>
   Кожа
  </material>
  <price>
   150216
  </price>
  <rating>
   3.78
  </rating>
  <reviews>
   837284
  </reviews>
  <new>
   -
  </new>
  <exclusive>
   no
  </exclusive>
  <sporty>
   yes
  </sporty>
 </clothing>
 <clothing>
  <id>
   853153565
  </id>
  <name>
   Vans Sweater Y-1911
  </name>
  <category>
   Sweater
  </category>
  <size>
   S
  </size>
  <color>
   Красный
  </color>
  <material>
   Шерсть
  </material>
  <price>
   654000
  </price>
  <rating>
   1.4
  </rating>
  <reviews>
   348983
  </reviews>
  <exclusive>
   no
  </exclusive>
  <sporty>
   no
  </sporty>
 </clothing>
 <clothing>
  <id>
   873629004
  </id>
  <name>
   Converse Hat X-9695
  </name>
  <category>
   Hat
  </category>
  <size>
   XXL
  </size>
  <color>
   Красный
  </color>
  <material>
   Вискоза
  </material>
  <price>
   132621
  </price>
  <rating>
   1.95
  </rating>
  <reviews>
   891328
  </reviews>
  <new>
   +
  </new>
 </clothing>
 <clothing>
  <id>
   300099281
  </id>
  <name>
   DC Pants R-5626
  </name>
  <category>
   Pants
  </category>
  <size>
   XL
  </size>
  <color>
   Синий
  </color>
  <material>
   Шерсть
  </material>
  <price>
   582545
  </price>
  <rating>
   3.88
  </rating>
  <reviews>
   554670
  </reviews>
  <new>
   +
  </new>
  <sporty>
   no
  </sporty>
 </clothing>
 <clothing>
  <id>
   909825521
  </id>
  <name>
   Ellesse Sweater P-5574
  </name>
  <category>
   Sweater
  </category>
  <size>
   XL
  </size>
  <color>
   Фиолетовый
  </color>
  <material>
   Хлопок
  </material>
  <price>
   845837
  </price>
  <rating>
   2.7
  </rating>
  <reviews>
   864847
  </reviews>
  <new>
   -
  </new>
  <exclusive>
   yes
  </exclusive>
  <sporty>
   no
  </sporty>
 </clothing>
 <clothing>
  <id>
   258346407
  </id>
  <name>
   New Balance Handbags F-6026
  </name>
  <category>
   Handbags
  </category>
  <size>
   XXL
  </size>
  <color>
   Оранжевый
  </color>
  <material>
   Шерсть
  </material>
  <price>
   981230
  </price>
  <rating>
   3.94
  </rating>
  <reviews>
   122596
  </reviews>
  <new>
   -
  </new>
  <sporty>
   no
  </sporty>
 </clothing>
 <clothing>
  <id>
   827223305
  </id>
  <name>
   Adidas Umbrellas V-5274
  </name>
  <category>
   Umbrellas
  </category>
  <size>
   XXL
  </size>
  <color>
   Зеленый
  </color>
  <material>
   Нейлон
  </material>
  <price>
   103749
  </price>
  <rating>
   1.68
  </rating>
  <reviews>
   205484
  </reviews>
  <new>
   +
  </new>
  <sporty>
   no
  </sporty>
 </clothing>
 <clothing>
  <id>
   628518259
  </id>
  <name>
   Ellesse Hat I-1338
  </name>
  <category>
   Hat
  </category>
  <size>
   S
  </size>
  <color>
   Голубой
  </color>
  <material>
   Вискоза
  </material>
  <price>
   977572
  </price>
  <rating>
   2.11
  </rating>
  <reviews>
   909039
  </reviews>
  <exclusive>
   yes
  </exclusive>
  <sporty>
   yes
  </sporty>
 </clothing>
 <clothing>
  <id>
   258420472
  </id>
  <name>
   Brooks Blouse L-2722
  </name>
  <category>
   Blouse
  </category>
  <size>
   XL
  </size>
  <color>
   Зеленый
  </color>
  <material>
   Хлопок
  </material>
  <price>
   582604
  </price>
  <rating>
   1.77
  </rating>
  <reviews>
   775995
  </reviews>
  <new>
   +
  </new>
  <exclusive>
   yes
  </exclusive>
 </clothing>
 <clothing>
  <id>
   926885446
  </id>
  <name>
   Ellesse T-shirt Z-2337
  </name>
  <category>
   T-shirt
  </category>
  <size>
   L
  </size>
  <color>
   Красный
  </color>
  <material>
   Хлопок
  </material>
  <price>
   131633
  </price>
  <rating>
   4.43
  </rating>
  <reviews>
   818990
  </reviews>
  <exclusive>
   no
  </exclusive>
  <sporty>
   yes
  </sporty>
 </clothing>
 <clothing>
  <id>
   346291802
  </id>
  <name>
   New Balance Umbrellas K-7508
  </name>
  <category>
   Umbrellas
  </category>
  <size>
   M
  </size>
  <color>
   Фиолетовый
  </color>
  <material>
   Лен
  </material>
  <price>
   630234
  </price>
  <rating>
   4.33
  </rating>
  <reviews>
   689298
  </reviews>
  <new>
   -
  </new>
 </clothing>
 <clothing>
  <id>
   636617009
  </id>
  <name>
   PleinSport Shirt I-4066
  </name>
  <category>
   Shirt
  </category>
  <size>
   S
  </size>
  <color>
   Желтый
  </color>
  <material>
   Нейлон
  </material>
  <price>
   244053
  </price>
  <rating>
   4.49
  </rating>
  <reviews>
   914426
  </reviews>
 </clothing>
 <clothing>
  <id>
   121916138
  </id>
  <name>
   Converse Shoes C-7762
  </name>
  <category>
   Shoes
  </category>
  <size>
   S
  </size>
  <color>
   Красный
  </color>
  <material>
   Полиэстер
  </material>
  <price>
   196468
  </price>
  <rating>
   3.74
  </rating>
  <reviews>
   165576
  </reviews>
  <new>
   -
  </new>
  <exclusive>
   no
  </exclusive>
  <sporty>
   no
  </sporty>
 </clothing>
 <clothing>
  <id>
   380722351
  </id>
  <name>
   Under Armour Shirt O-8358
  </name>
  <category>
   Shirt
  </category>
  <size>
   XL
  </size>
  <color>
   Синий
  </color>
  <material>
   Кожа
  </material>
  <price>
   307475
  </price>
  <rating>
   4.92
  </rating>
  <reviews>
   791174
  </reviews>
  <new>
   +
  </new>
  <exclusive>
   no
  </exclusive>
 </clothing>
 <clothing>
  <id>
   699176230
  </id>
  <name>
   Vans Blouse W-5856
  </name>
  <category>
   Blouse
  </category>
  <size>
   S
  </size>
  <color>
   Красный
  </color>
  <material>
   Хлопок
  </material>
  <price>
   922515
  </price>
  <rating>
   2.5
  </rating>
  <reviews>
   482108
  </reviews>
  <new>
   -
  </new>
 </clothing>
 <clothing>
  <id>
   512100266
  </id>
  <name>
   Converse Sweater O-3856
  </name>
  <category>
   Sweater
  </category>
  <size>
   M
  </size>
  <color>
   Голубой
  </color>
  <material>
   Шерсть
  </material>
  <price>
   232457
  </price>
  <rating>
   3.73
  </rating>
  <reviews>
   240880
  </reviews>
  <sporty>
   no
  </sporty>
 </clothing>
 <clothing>
  <id>
   954909488
  </id>
  <name>
   Ellesse Dress Z-3798
  </name>
  <category>
   Dress
  </category>
  <size>
   M
  </size>
  <color>
   Красный
  </color>
  <material>
   Лен
  </material>
  <price>
   763851
  </price>
  <rating>
   1.23
  </rating>
  <reviews>
   582650
  </reviews>
  <new>
   -
  </new>
  <exclusive>
   no
  </exclusive>
 </clothing>
</clothing-items>
